{
  "training_examples": [
    {
      "input": "SOFTWARE LICENSE AGREEMENT\nContract Number: SLA-2024-001\nDate: January 15, 2024\n\nPARTIES:\nVendor: TechSolutions Inc.\nAddress: 123 Innovation Drive, Tech City, CA 90210\nEmail: contracts@techsolutions.com\nPhone: (555) 123-4567\n\nClient: Business Corp\nAddress: 456 Corporate Blvd, Business City, NY 10001\nContact: John Smith, Procurement Manager\nEmail: john.smith@businesscorp.com\nPhone: (555) 987-6543\n\nCONTRACT VALUE: $75,000 annually\nCurrency: USD\nPayment Schedule: Annual payment in advance\n\nPAYMENT TERMS: Net 30 days from invoice date\nAll invoices must be submitted by the 25th of each month.\nLate payment penalty: 1.5% per month on outstanding amounts.\n\nDELIVERY TERMS: Standard delivery within 5-7 business days\nSoftware deployment and training included.\nSupport: 24/7 technical support included.\n\nCOMPLIANCE: This agreement complies with all industry standards and \nincludes required data protection clauses per GDPR requirements.\nAll software meets SOC 2 Type II compliance standards.\n\nTERMINATION: Either party may terminate with 90 days written notice.\nUpon termination, client retains limited license for 30 days for data migration.\n\nGOVERNING LAW: This agreement shall be governed by the laws of California.\nAny disputes shall be resolved through binding arbitration in Los Angeles, CA.",
      "output": {
        "payment_terms": {
          "extracted_text": "Net 30 days from invoice date",
          "classification": "standard",
          "standardized_value": "Net 30"
        },
        "contract_value": {
          "extracted_text": "$75,000 annually",
          "amount": 75000,
          "currency": "USD",
          "classification": "medium_value"
        },
        "delivery_terms": {
          "extracted_text": "Standard delivery within 5-7 business days",
          "classification": "standard_shipping",
          "delivery_timeframe": "5-7 business days"
        },
        "compliance_requirements": {
          "extracted_text": "This agreement complies with all industry standards and includes required data protection clauses per GDPR requirements. All software meets SOC 2 Type II compliance standards.",
          "classification": "fully_compliant",
          "missing_elements": []
        },
        "contact_information": {
          "extracted_contacts": [
            {
              "name": "John Smith",
              "email": "john.smith@businesscorp.com",
              "phone": "(555) 987-6543",
              "role": "Procurement Manager"
            },
            {
              "name": "TechSolutions Inc.",
              "email": "contracts@techsolutions.com",
              "phone": "(555) 123-4567",
              "role": "Vendor"
            }
          ],
          "classification": "complete"
        },
        "document_type": "contract",
        "priority_level": "medium"
      },
      "metadata": {
        "document_file": "contract_001.txt",
        "labels_file": "contract_001.labels.json",
        "document_type": "contract"
      }
    },
    {
      "input": "URGENT: RUSH DELIVERY CONTRACT\nContract ID: RUSH-2024-002\nDate: February 20, 2024\n\nPRIORITY: HIGH - IMMEDIATE ATTENTION REQUIRED\n\nThis is a high-priority contract requiring immediate attention and processing.\n\nPAYMENT TERMS: Payment due within 120 days of project completion\nwith a 5% early payment discount if paid within 10 days. \nSpecial arrangement negotiated for this preferred vendor client\ndue to their long-standing relationship and credit history.\n\nCONTRACT VALUE: $2,500,000 (Two Million Five Hundred Thousand USD)\nThis represents a significant enterprise engagement requiring\nexecutive approval and additional oversight.\n\nDELIVERY TERMS: RUSH DELIVERY - All components must be delivered\nwithin 24 hours of order confirmation. Expedited shipping required.\nSpecial handling fees apply for rush orders.\n\nCOMPLIANCE NOTE: This contract is missing standard compliance\nclauses and requires legal review before execution.\nData protection requirements need to be added.\nInsurance requirements are not specified.\n\nCONTACT INFORMATION:\nPrimary: Sarah Wilson, VP Operations\nEmail: urgent@company.com\nPhone: 555-URGENT (555-874-3689)\nMobile: (555) 999-1234\n\nSecondary: Mike Chen, Legal Counsel\nEmail: legal@company.com\nPhone: (555) 555-0199\n\nGOVERNING LAW: New York State\nTERMINATION: Immediate termination allowed for non-performance",
      "output": {
        "payment_terms": {
          "extracted_text": "Payment due within 120 days of project completion with a 5% early payment discount if paid within 10 days",
          "classification": "non_standard",
          "standardized_value": "120 days with 5% discount/10 days"
        },
        "contract_value": {
          "extracted_text": "$2,500,000 (Two Million Five Hundred Thousand USD)",
          "amount": 2500000,
          "currency": "USD",
          "classification": "enterprise"
        },
        "delivery_terms": {
          "extracted_text": "RUSH DELIVERY - All components must be delivered within 24 hours of order confirmation. Expedited shipping required.",
          "classification": "rush",
          "delivery_timeframe": "24 hours"
        },
        "compliance_requirements": {
          "extracted_text": "This contract is missing standard compliance clauses and requires legal review before execution. Data protection requirements need to be added. Insurance requirements are not specified.",
          "classification": "requires_review",
          "missing_elements": [
            "data protection clauses",
            "insurance requirements",
            "standard compliance clauses"
          ]
        },
        "contact_information": {
          "extracted_contacts": [
            {
              "name": "Sarah Wilson",
              "email": "urgent@company.com",
              "phone": "(555) 874-3689",
              "role": "VP Operations"
            },
            {
              "name": "Mike Chen",
              "email": "legal@company.com",
              "phone": "(555) 555-0199",
              "role": "Legal Counsel"
            }
          ],
          "classification": "complete"
        },
        "document_type": "contract",
        "priority_level": "urgent"
      },
      "metadata": {
        "document_file": "contract_002.txt",
        "labels_file": "contract_002.labels.json",
        "document_type": "contract"
      }
    },
    {
      "input": "CONSULTING AGREEMENT\nContract Number: CONS-2024-003\nDate: March 10, 2024\n\nThis agreement outlines consulting services for business process optimization.\n\nPARTIES:\nConsultant: Strategic Solutions LLC\nClient: Mid-Size Corp\n\nPAYMENT ARRANGEMENT: Payment will be arranged separately through\nour finance department. Terms to be negotiated based on project scope.\nHourly rates apply for additional work beyond base scope.\n\nCONTRACT VALUE: To be determined based on final scope\nEstimated range: $25,000 - $50,000\n\nSERVICES: Strategic consulting and process improvement\nDeliverables include analysis report and implementation roadmap.\n\nDELIVERY: Services will be delivered as needed over 6-month period.\nNo specific delivery timeline established.\n\nCOMPLIANCE: Standard business practices apply.\nNo specific regulatory requirements identified.\n\nCONTACT: For questions, please contact our office.\nMain office: (555) 123-0000\nProject inquiries: consulting@strategic.com\n\nTERMS: This is a preliminary agreement.\nFinal terms subject to negotiation and formal contract execution.",
      "output": {
        "payment_terms": {
          "extracted_text": "Payment will be arranged separately through our finance department. Terms to be negotiated based on project scope.",
          "classification": "unknown",
          "standardized_value": "TBD"
        },
        "contract_value": {
          "extracted_text": "To be determined based on final scope. Estimated range: $25,000 - $50,000",
          "amount": 37500,
          "currency": "USD",
          "classification": "medium_value"
        },
        "delivery_terms": {
          "extracted_text": "Services will be delivered as needed over 6-month period. No specific delivery timeline established.",
          "classification": "custom_delivery",
          "delivery_timeframe": "6-month period"
        },
        "compliance_requirements": {
          "extracted_text": "Standard business practices apply. No specific regulatory requirements identified.",
          "classification": "partially_compliant",
          "missing_elements": [
            "specific compliance requirements",
            "data protection clauses"
          ]
        },
        "contact_information": {
          "extracted_contacts": [
            {
              "name": "Strategic Solutions LLC",
              "email": "consulting@strategic.com",
              "phone": "(555) 123-0000",
              "role": "Consultant"
            }
          ],
          "classification": "partial"
        },
        "document_type": "contract",
        "priority_level": "low"
      },
      "metadata": {
        "document_file": "contract_003.txt",
        "labels_file": "contract_003.labels.json",
        "document_type": "contract"
      }
    },
    {
      "input": "PROFESSIONAL SERVICES AGREEMENT\n        Contract Number: PSA-2024-004\n        Date: August 20, 2025\n        \n        CONSULTING SERVICES for Digital Transformation\n        \n        CLIENT: Innovation Corp\n        VENDOR: Digital Solutions LLC\n        Contact: Sarah Wilson, Project Manager\n        Email: sarah@digitalsolutions.com\n        Phone: (555) 888-9999\n        \n        CONTRACT VALUE: $125,000 for 6-month engagement\n        Payment Schedule: Monthly payments of $20,833.33\n        \n        PAYMENT TERMS: Net 15 days from invoice date\n        Monthly invoicing on the 1st of each month.\n        \n        DELIVERY: Services delivered remotely with weekly check-ins.\n        Final deliverables due within 180 days of contract start.\n        \n        COMPLIANCE: Standard professional services agreement.\n        Confidentiality and IP protection clauses included.\n        \n        This agreement requires client approval before execution.",
      "output": {
        "payment_terms": {
          "extracted_text": "Net 15 days from invoice date",
          "classification": "standard",
          "standardized_value": "Net 15"
        },
        "contract_value": {
          "extracted_text": "$125,000",
          "amount": 125000,
          "currency": "USD",
          "classification": "high_value"
        },
        "document_type": "contract",
        "priority_level": "medium"
      },
      "metadata": {
        "document_file": "contract_004_example.txt",
        "labels_file": "contract_004_example.labels.json",
        "document_type": "contract"
      }
    }
  ],
  "metadata": {
    "total_examples": 4,
    "export_source": "C:\\Users\\suraj\\Desktop\\SOURCE\\langextract\\docuverse\\data\\contracts",
    "validation_report": {
      "total_documents": 4,
      "valid_pairs": 4,
      "invalid_pairs": 0,
      "missing_labels": [],
      "missing_documents": [],
      "validation_errors": [],
      "field_coverage": {
        "payment_terms": 4,
        "contract_value": 4,
        "delivery_terms": 3,
        "compliance_requirements": 3,
        "contact_information": 3,
        "document_type": 4,
        "priority_level": 4
      },
      "document_types": {
        "contract": 4
      }
    }
  }
}